README.txt
setup.py
Khayyam3.egg-info/PKG-INFO
Khayyam3.egg-info/SOURCES.txt
Khayyam3.egg-info/dependency_links.txt
Khayyam3.egg-info/top_level.txt
Khayyam3.egg-info/zip-safe
khayyam3/__init__.py
khayyam3/algorithms.py
khayyam3/jalali_date.py
khayyam3/jalali_datetime.py
khayyam3/tehran_timezone.py